{
  "data": {
    "className": "MigrationsLock",
    "properties": {
      "index": {
        "name": "index",
        "reference": "scalar",
        "primary": true,
        "type": "number"
      },
      "isLocked": {
        "name": "isLocked",
        "reference": "scalar",
        "nullable": true,
        "getter": false,
        "setter": false,
        "type": "number"
      }
    },
    "hooks": {},
    "filters": {},
    "primaryKeys": [
      "index"
    ],
    "indexes": [],
    "uniques": [],
    "path": "./src/bot/entities/MigrationsLock.ts",
    "name": "MigrationsLock",
    "abstract": false,
    "constructorParams": [],
    "toJsonParams": [],
    "useCache": true,
    "compositePK": false,
    "props": [
      {
        "name": "index",
        "reference": "scalar",
        "primary": true,
        "type": "number"
      },
      {
        "name": "isLocked",
        "reference": "scalar",
        "nullable": true,
        "getter": false,
        "setter": false,
        "type": "number"
      }
    ],
    "collection": "migrations_lock"
  },
  "origin": "./src/bot/entities/MigrationsLock.ts",
  "hash": "b2995f90db1cc21d3e883d43f0f53b2c",
  "version": "4.0.7"
}
